{
    "struct":
    [
        {
            "abd"            : "<asset",
            "abr"            : "<asset",
            "unknown_0x10"   : {"type": "<int32",   "label": "" },
            "unknown_0x14"   : {"type": "<float32", "label": "" },
            "unknown_0x18"   : {"type": "<float32", "label": "" },
            "unknown_0x1C"   : {"type": "<float32", "label": "" },
            "unknown_0x20"   : {"type": "<float32", "label": "" },
            "unknown_0x24"   : {"type": "<float32", "label": "" },
            "unknown_0x28"   : {"type": "<float32", "label": "" },
            "unknown_0x2C"   : {"type": "<float32", "label": "" },
            "unknown_0x30"   : {"type": "<float32", "label": "All Range Mod" },
            "unknown_0x34"   : {"type": "<float32", "label": "" },
            "unknown_0x38"   : {"type": "<int32",   "label": "" },
            "unknown_0x3C"   : {"type": "<float32", "label": "" },
            "unknown_0x40"   : {"type": "<float32", "label": "" },
            "unknown_0x44"   : {"type": "<float32", "label": "" },
            "unknown_0x48"   : {"type": "<float32", "label": "" },
            "unknown_0x4C"   : {"type": "<float32", "label": "" },
            "unknown_0x50"   : {"type": "<int32",   "label": "" },
            "unknown_0x54"   : {"type": "<float32", "label": "" },
            "unknown_0x58"   : {"type": "<float32", "label": "Easy Difficulty Mod" },
            "unknown_0x5C"   : {"type": "<float32", "label": "" },
            "unknown_0x60"   : {"type": "<float32", "label": "" },
            "unknown_0x64"   : {"type": "<float32", "label": "" },
            "unknown_0x68"   : {"type": "<float32", "label": "" },
            "unknown_0x6C"   : {"type": "<float32", "label": "" },
            "unknown_0x70"   : {"type": "<float32", "label": "" },
            "unknown_0x74"   : {"type": "<float32", "label": "" },
            "unknown_0x78"   : {"type": "<float32", "label": "" },
            "unknown_0x7C"   : {"type": "<float32", "label": "" },
            "unknown_0x80"   : {"type": "<float32", "label": "" },
            "unknown_0x84"   : {"type": "<float32", "label": "" },
            "unknown_0x88"   : {"type": "<float32", "label": "" },
            "unknown_0x8C"   : {"type": "<float32", "label": "" },
            "unknown_0x90"   : {"type": "<float32", "label": "" },
            "unknown_0x94"   : {"type": "<int32",   "label": "" },
            "unknown_0x98"   : {"type": "<float32", "label": "" },
            "unknown_0x9C"   : {"type": "<float32", "label": "" },
            "unknown_0xA0"   : {"type": "<float32", "label": "" },
            "unknown_0xA4"   : {"type": "<float32", "label": "" },
            "unknown_0xA8"   : {"type": "<float32", "label": "" },
            "unknown_0xAC"   : {"type": "<float32", "label": "" },
            "unknown_0xB0"   : {"type": "<int32",   "label": "" },
            "unknown_0xB4"   : {"type": "<float32", "label": "" },
            "unknown_0xB8"   : {"type": "<float32", "label": "" },
            "unknown_0xBC"   : {"type": "<float32", "label": "" },
            "unknown_0xC0"   : {"type": "<float32", "label": "" },
            "unknown_0xC4"   : {"type": "<float32", "label": "" },
            "unknown_0xC8"   : {"type": "<float32", "label": "" },
            "unknown_0xCC"   : {"type": "<float32", "label": "" },
            "unknown_0xD0"   : {"type": "<float32", "label": "" },
            "unknown_0xD4"   : {"type": "<float32", "label": "" },
            "unknown_0xD8"   : {"type": "<float32", "label": "" },
            "unknown_0xDC"   : {"type": "<float32", "label": "" },
            "unknown_0xE0"   : {"type": "<float32", "label": "" },
            "unknown_0xE4"   : {"type": "<float32", "label": "" },
            "unknown_0xE8"   : {"type": "<float32", "label": "" },
            "unknown_0xEC"   : {"type": "<float32", "label": "" },
            "unknown_0xF0"   : {"type": "<float32", "label": "" },
            "unknown_0xF4"   : {"type": "<float32", "label": "" },
            "unknown_0xF8"   : {"type": "<float32", "label": "" },
            "unknown_0xFC"   : {"type": "<float32", "label": "" },
            "unknown_0x0100" : {"type": "<float32", "label": "" },
            "unknown_0x0104" : {"type": "<float32", "label": "" },
            "unknown_0x0108" : {"type": "<float32", "label": "" },
            "unknown_0x010C" : {"type": "<float32", "label": "" },
            "unknown_0x0110" : {"type": "<float32", "label": "" },
            "unknown_0x0114" : {"type": "<float32", "label": "" },
            "unknown_0x0118" : {"type": "<int32",   "label": "" },
            "unknown_0x011C" : {"type": "<float32", "label": "" },
            "unknown_0x0120" : {"type": "<int32",   "label": "" },
            "unknown_0x0124" : {"type": "<int32",   "label": "" },
            "unknown_0x0128" : {"type": "<int32",   "label": "" },
            "unknown_0x012C" : {"type": "<float32", "label": "" },
            "unknown_0x0130" : {"type": "<int32",   "label": "" },
            "unknown_0x0134" : {"type": "<int32",   "label": "" },
            "unknown_0x0138" : {"type": "<int32",   "label": "" },
            "unknown_0x013C" : {"type": "<int32",   "label": "" }
        }
    ],
    "assets":
    {
        "abd": "abd",
        "abr": "abr"
    }
}
