{
    "struct":
    [
        {
            "0x00"   : {"type": "<float32", "label": "Pass Def" },
            "0x04"   : {"type": "<float32", "label": "Pass VsP" },
            "0x08"   : {"type": "<float32", "label": "Pass VsA" },
            "0x0C"   : {"type": "<float32", "label": "High Morale Negative Chance Reduction" },
            "0x10"   : {"type": "<float32", "label": "High Morale Last Stand Chance" },
            "0x14"   : {"type": "<int16",   "label": "Base Kill Morale" },
            "0x16"   : {"type": "<int16",   "label": "Base Tank Morale" },
            "0x18"   : {"type": "<int16",   "label": "Base Camp Morale" },
            "0x1A"   : {"type": "<int16",   "label": "Base Heal Morale" },
            "0x1C"   : {"type": "<int16",   "label": "??? not HM threshold, not stand up +AP, not order" },
            "0x1E"   : {"type": "<int16",   "label": "Inspire Pass Morale" }
        }
    ]
}
